setup.py
twistedhttpstream/__init__.py
twistedhttpstream/stream.py
twistedhttpstream.egg-info/PKG-INFO
twistedhttpstream.egg-info/SOURCES.txt
twistedhttpstream.egg-info/dependency_links.txt
twistedhttpstream.egg-info/top_level.txt