Metadata-Version: 1.0
Name: twistedhttpstream
Version: 0.0.1
Summary: Twisted client library for the HTTP Stream
Home-page: https://github.com/rande/twisted-http-stream
Author: Thomas Rabaix, Alexandre Fiori
Author-email: thomas.rabaix@gmail.com
License: UNKNOWN
Platform: UNKNOWN
